Image_Search/ImageSearch.py
Image_Search/SearchTags.py
PythonImageSearch-1.0.4.dist-info/METADATA
PythonImageSearch-1.0.4.dist-info/WHEEL
PythonImageSearch-1.0.4.dist-info/top_level.txt
PythonImageSearch-1.0.4.dist-info/RECORD
