Metadata-Version: 2.1
Name: PythonImageSearch
Version: 1.0.4
Summary: Simple image search
Home-page: https://github.com/RandomPythonProgrammer/python-image-search
Author: RandomPythonProgrammer
Author-email: jhc3628@gmail.com
License: UNKNOWN
Keywords: Image Search
Platform: UNKNOWN
Requires-Dist: selenium
Requires-Dist: bs4
Requires-Dist: requests
